CHANGELOG.rst
LICENSE
MANIFEST.in
README.rst
romkan.json
setup.py
src/romkan/__init__.py
src/romkan/common.py
src/romkan/version.py
src/romkan.egg-info/PKG-INFO
src/romkan.egg-info/SOURCES.txt
src/romkan.egg-info/dependency_links.txt
src/romkan.egg-info/not-zip-safe
src/romkan.egg-info/top_level.txt
tests/__init__.py
tests/test.py